setup.py
unicodeblocks/__init__.py
unicodeblocks/__main__.py
unicodeblocks/_blocklist.py
unicodeblocks/_unicodeblocks.py
unicodeblocks/blocklist.py
unicodeblocks.egg-info/PKG-INFO
unicodeblocks.egg-info/SOURCES.txt
unicodeblocks.egg-info/dependency_links.txt
unicodeblocks.egg-info/not-zip-safe
unicodeblocks.egg-info/top_level.txt