Metadata-Version: 1.1
Name: unicodeblocks
Version: 0.3
Summary: Python module for unicode blocks
Home-page: https://github.com/simukis/unicodeblocks
Author: Simonas Kazlauskas
Author-email: UNKNOWN
License: ISC
Platform: UNKNOWN
Classifier: Development Status :: 4 - Beta
Classifier: Intended Audience :: Developers
Classifier: Operating System :: OS Independent
Classifier: License :: OSI Approved :: ISC License (ISCL)
Classifier: Programming Language :: Python
Classifier: Programming Language :: Python :: 3.1
Classifier: Programming Language :: Python :: 3.2
Classifier: Programming Language :: Python :: 3.3
Classifier: Topic :: Utilities
